multiflow/__init__.py
multiflow/thread.py
multiflow/utils.py
multiflow/version.py
multiflow-1.0.4.dist-info/LICENSE
multiflow-1.0.4.dist-info/METADATA
multiflow-1.0.4.dist-info/WHEEL
multiflow-1.0.4.dist-info/top_level.txt
multiflow-1.0.4.dist-info/RECORD
