Metadata-Version: 2.1
Name: multiflow
Version: 1.0.4
Summary: A Python multithreading library for data processing pipelines, data streaming, etc.
Home-page: https://github.com/nyoungstudios/multiflow
Author: Nathaniel Young
Author-email: 
Maintainer: Nathaniel Young
Maintainer-email: 
License: MIT
Keywords: multiflow multithreading data processing streaming concurrent futures python
Platform: UNKNOWN
Classifier: Intended Audience :: Developers
Classifier: Operating System :: OS Independent
Classifier: Programming Language :: Python :: 3
Classifier: Topic :: Scientific/Engineering
Classifier: Topic :: System :: Distributed Computing
Classifier: Topic :: Utilities
License-File: LICENSE
